nonpoisonous/__init__.py
nonpoisonous/main.py
nonpoisonous-0.0.1.dist-info/METADATA
nonpoisonous-0.0.1.dist-info/WHEEL
nonpoisonous-0.0.1.dist-info/entry_points.txt
nonpoisonous-0.0.1.dist-info/top_level.txt
nonpoisonous-0.0.1.dist-info/RECORD
