Metadata-Version: 2.1
Name: nonpoisonous
Version: 0.0.1
Summary: A nonpoisonous dataset
Author: Romlin Group AB
Author-email: hello@romlin.com
